{
	"name": "Prototype01_ES",
	"events": [
		{
			"eventType": "variable",
			"name": "LevelUp",
			"type": "boolean",
			"initialValue": "false",
			"comment": "",
			"isStatic": false,
			"isConstant": false,
			"sid": 331056608074654
		},
		{
			"eventType": "comment",
			"text": "Do not delete"
		},
		{
			"eventType": "block",
			"conditions": [
				{
					"id": "on-clicked",
					"objectClass": "Menu_Button",
					"sid": 924659407202461
				}
			],
			"actions": [
				{
					"id": "go-to-layout",
					"objectClass": "System",
					"sid": 168821516711458,
					"parameters": {
						"layout": "MenuPrototype"
					}
				}
			],
			"sid": 970608049604052
		},
		{
			"eventType": "group",
			"disabled": false,
			"title": "PlayerFunctions",
			"description": "",
			"isActiveOnStart": true,
			"children": [
				{
					"eventType": "group",
					"disabled": false,
					"title": "Leveling",
					"description": "",
					"isActiveOnStart": true,
					"children": [
						{
							"eventType": "block",
							"conditions": [
								{
									"id": "compare-instance-variable",
									"objectClass": "Player",
									"sid": 605940130262670,
									"parameters": {
										"instance-variable": "Experience",
										"comparison": 0,
										"value": "20"
									}
								},
								{
									"id": "compare-boolean-eventvar",
									"objectClass": "System",
									"sid": 501960774277360,
									"parameters": {
										"variable": "LevelUp"
									},
									"isInverted": true
								}
							],
							"actions": [
								{
									"id": "set-boolean-eventvar",
									"objectClass": "System",
									"sid": 232382603258702,
									"parameters": {
										"variable": "LevelUp",
										"value": "true"
									}
								},
								{
									"id": "add-to-instvar",
									"objectClass": "Player",
									"sid": 928718726352815,
									"parameters": {
										"instance-variable": "Experience",
										"value": "1"
									}
								}
							],
							"sid": 864132376805533
						},
						{
							"eventType": "block",
							"conditions": [
								{
									"id": "compare-instance-variable",
									"objectClass": "Player",
									"sid": 426415719074997,
									"parameters": {
										"instance-variable": "Experience",
										"comparison": 0,
										"value": "61"
									}
								},
								{
									"id": "compare-boolean-eventvar",
									"objectClass": "System",
									"sid": 296456545885985,
									"parameters": {
										"variable": "LevelUp"
									},
									"isInverted": true
								}
							],
							"actions": [
								{
									"id": "set-boolean-eventvar",
									"objectClass": "System",
									"sid": 608018344330648,
									"parameters": {
										"variable": "LevelUp",
										"value": "true"
									}
								},
								{
									"id": "add-to-instvar",
									"objectClass": "Player",
									"sid": 838509318156517,
									"parameters": {
										"instance-variable": "Experience",
										"value": "1"
									}
								}
							],
							"sid": 600922902125155
						},
						{
							"eventType": "block",
							"conditions": [
								{
									"id": "compare-instance-variable",
									"objectClass": "Player",
									"sid": 271231922637374,
									"parameters": {
										"instance-variable": "Experience",
										"comparison": 0,
										"value": "122"
									}
								},
								{
									"id": "compare-boolean-eventvar",
									"objectClass": "System",
									"sid": 619895465929096,
									"parameters": {
										"variable": "LevelUp"
									},
									"isInverted": true
								}
							],
							"actions": [
								{
									"id": "set-boolean-eventvar",
									"objectClass": "System",
									"sid": 754822934727073,
									"parameters": {
										"variable": "LevelUp",
										"value": "true"
									}
								},
								{
									"id": "add-to-instvar",
									"objectClass": "Player",
									"sid": 530799715992290,
									"parameters": {
										"instance-variable": "Experience",
										"value": "1"
									}
								}
							],
							"sid": 162810629648235
						},
						{
							"eventType": "block",
							"conditions": [
								{
									"id": "compare-boolean-eventvar",
									"objectClass": "System",
									"sid": 631362697165962,
									"parameters": {
										"variable": "LevelUp"
									}
								}
							],
							"actions": [
								{
									"id": "set-boolean-eventvar",
									"objectClass": "System",
									"sid": 725304520610555,
									"parameters": {
										"variable": "LevelUp",
										"value": "false"
									}
								},
								{
									"id": "add-to-instvar",
									"objectClass": "Player",
									"sid": 825629543799850,
									"parameters": {
										"instance-variable": "Level",
										"value": "1"
									}
								},
								{
									"id": "add-to-instvar",
									"objectClass": "Player",
									"sid": 828216354965077,
									"parameters": {
										"instance-variable": "Health",
										"value": "2"
									}
								},
								{
									"id": "add-to-instvar",
									"objectClass": "Player",
									"sid": 766452912138690,
									"parameters": {
										"instance-variable": "MeleeAttackPower",
										"value": "1"
									}
								}
							],
							"sid": 615933385256578
						}
					],
					"sid": 535631735807290
				},
				{
					"eventType": "group",
					"disabled": false,
					"title": "Interactions",
					"description": "",
					"isActiveOnStart": true,
					"children": [
						{
							"eventType": "block",
							"conditions": [
								{
									"id": "is-overlapping-another-object",
									"objectClass": "Player",
									"sid": 224544909784639,
									"parameters": {
										"object": "Chests"
									}
								}
							],
							"actions": [],
							"sid": 388691669016701,
							"children": [
								{
									"eventType": "block",
									"conditions": [
										{
											"id": "on-key-pressed",
											"objectClass": "Keyboard",
											"sid": 548004009042781,
											"parameters": {
												"key": 69
											}
										}
									],
									"actions": [
										{
											"id": "set-animation",
											"objectClass": "Chest",
											"sid": 674637976754006,
											"parameters": {
												"animation": "\"Open\"",
												"from": "beginning"
											}
										},
										{
											"id": "set-collisions-enabled",
											"objectClass": "Chest",
											"sid": 721527972919896,
											"parameters": {
												"collisions": "disabled"
											}
										},
										{
											"id": "set-visible",
											"objectClass": "PuBow",
											"sid": 113814678090978,
											"parameters": {
												"visibility": "visible"
											}
										},
										{
											"id": "wait",
											"objectClass": "System",
											"sid": 302260274377140,
											"parameters": {
												"seconds": "2"
											}
										},
										{
											"id": "set-collisions-enabled",
											"objectClass": "PuBow",
											"sid": 265694093937056,
											"parameters": {
												"collisions": "enabled"
											}
										}
									],
									"sid": 395623629597439
								}
							]
						},
						{
							"eventType": "block",
							"conditions": [
								{
									"id": "on-collision-with-another-object",
									"objectClass": "ProjEnemyArrows",
									"sid": 726961012729413,
									"parameters": {
										"object": "Player"
									}
								}
							],
							"actions": [
								{
									"id": "destroy",
									"objectClass": "ProjEnemyArrows",
									"sid": 362234279975610
								},
								{
									"id": "subtract-from-instvar",
									"objectClass": "Player",
									"sid": 985742653956007,
									"parameters": {
										"instance-variable": "Health",
										"value": "Enemies.AttackPower"
									}
								},
								{
									"id": "set-speed",
									"objectClass": "ProjEnemyArrows",
									"sid": 487069425813937,
									"behaviorType": "Bullet",
									"parameters": {
										"speed": "ProjEnemyArrows.ProjectileSpeed"
									}
								}
							],
							"sid": 498435443279404
						},
						{
							"eventType": "block",
							"conditions": [
								{
									"id": "on-collision-with-another-object",
									"objectClass": "ProjEnemyArrows",
									"sid": 633093863531950,
									"parameters": {
										"object": "TiMWalls"
									}
								}
							],
							"actions": [
								{
									"id": "destroy",
									"objectClass": "ProjEnemyArrows",
									"sid": 485246732767382
								}
							],
							"sid": 895092828741998
						},
						{
							"eventType": "block",
							"conditions": [
								{
									"id": "on-collision-with-another-object",
									"objectClass": "Player",
									"sid": 431622634775696,
									"parameters": {
										"object": "PuBow"
									}
								}
							],
							"actions": [
								{
									"id": "set-boolean-instvar",
									"objectClass": "Player",
									"sid": 529427349827497,
									"parameters": {
										"instance-variable": "HasWeapon",
										"value": "true"
									}
								},
								{
									"id": "destroy",
									"objectClass": "PuBow",
									"sid": 555106935734231
								},
								{
									"id": "set-visible",
									"objectClass": "TxtTooltip",
									"sid": 226921056310963,
									"parameters": {
										"visibility": "visible"
									}
								},
								{
									"id": "set-text",
									"objectClass": "TxtTooltip",
									"sid": 738962659975969,
									"parameters": {
										"text": "\"Use the Left Mouse Button to swing your axe.\""
									}
								},
								{
									"id": "wait",
									"objectClass": "System",
									"sid": 791011420586468,
									"parameters": {
										"seconds": "2"
									}
								},
								{
									"id": "set-visible",
									"objectClass": "TxtTooltip",
									"sid": 303460825719569,
									"parameters": {
										"visibility": "invisible"
									}
								}
							],
							"sid": 856892549012274
						},
						{
							"eventType": "block",
							"conditions": [
								{
									"id": "is-overlapping-another-object",
									"objectClass": "Player",
									"sid": 430816054703919,
									"parameters": {
										"object": "Switch"
									}
								}
							],
							"actions": [],
							"sid": 313938740384485,
							"children": [
								{
									"eventType": "block",
									"conditions": [
										{
											"id": "on-key-pressed",
											"objectClass": "Keyboard",
											"sid": 924488266385917,
											"parameters": {
												"key": 69
											}
										}
									],
									"actions": [],
									"sid": 382602219393629,
									"children": [
										{
											"eventType": "block",
											"conditions": [
												{
													"id": "is-boolean-instance-variable-set",
													"objectClass": "Switch",
													"sid": 952237504439900,
													"parameters": {
														"instance-variable": "TurnOffTurrets"
													}
												}
											],
											"actions": [
												{
													"id": "set-boolean-instvar",
													"objectClass": "Switch",
													"sid": 339840732108161,
													"parameters": {
														"instance-variable": "TurnOffTurrets",
														"value": "false"
													}
												},
												{
													"id": "set-range",
													"objectClass": "RangedEnemy",
													"sid": 993995705195751,
													"behaviorType": "LineOfSight",
													"parameters": {
														"range": "0"
													}
												},
												{
													"id": "set-enabled",
													"objectClass": "RangedEnemy",
													"sid": 694424873266561,
													"behaviorType": "Turret",
													"parameters": {
														"state": "disabled"
													}
												}
											],
											"sid": 545254709297835,
											"children": [
												{
													"eventType": "block",
													"conditions": [
														{
															"id": "compare-instance-variable",
															"objectClass": "MeleeEnemy",
															"sid": 401878582751874,
															"parameters": {
																"instance-variable": "SpawnNum",
																"comparison": 0,
																"value": "1"
															}
														}
													],
													"actions": [
														{
															"id": "set-visible",
															"objectClass": "MeleeEnemy",
															"sid": 896995186433688,
															"parameters": {
																"visibility": "visible"
															}
														},
														{
															"id": "set-collisions-enabled",
															"objectClass": "MeleeEnemy",
															"sid": 220266622733243,
															"parameters": {
																"collisions": "enabled"
															}
														},
														{
															"id": "set-enabled",
															"objectClass": "MeleeEnemy",
															"sid": 953487831593075,
															"behaviorType": "MoveTo",
															"parameters": {
																"enabled": true
															}
														}
													],
													"sid": 334710158300052
												}
											]
										},
										{
											"eventType": "block",
											"conditions": [
												{
													"id": "compare-instance-variable",
													"objectClass": "MoveableWall",
													"sid": 436936229230431,
													"parameters": {
														"instance-variable": "DoorNumbers",
														"comparison": 0,
														"value": "Switch.DoorNumber"
													}
												}
											],
											"actions": [
												{
													"id": "set-enabled",
													"objectClass": "MoveableWall",
													"sid": 158261617953899,
													"behaviorType": "Solid",
													"parameters": {
														"state": "disabled"
													}
												},
												{
													"id": "set-visible",
													"objectClass": "MoveableWall",
													"sid": 899663176433278,
													"parameters": {
														"visibility": "toggle"
													}
												},
												{
													"id": "set-animation",
													"objectClass": "Switch",
													"sid": 171258779565356,
													"parameters": {
														"animation": "\"Lit\"",
														"from": "beginning"
													}
												},
												{
													"id": "set-visible",
													"objectClass": "TxtTooltip",
													"sid": 804662526010382,
													"parameters": {
														"visibility": "visible"
													}
												},
												{
													"id": "set-text",
													"objectClass": "TxtTooltip",
													"sid": 853105412166907,
													"parameters": {
														"text": "\"You hear the sound of doors opening...\""
													}
												},
												{
													"id": "wait",
													"objectClass": "System",
													"sid": 191985505524795,
													"parameters": {
														"seconds": "2"
													}
												},
												{
													"id": "set-visible",
													"objectClass": "TxtTooltip",
													"sid": 298284943915976,
													"parameters": {
														"visibility": "invisible"
													}
												}
											],
											"sid": 444249522847280
										}
									]
								}
							]
						},
						{
							"eventType": "block",
							"conditions": [
								{
									"id": "on-collision-with-another-object",
									"objectClass": "Player",
									"sid": 533621894547023,
									"parameters": {
										"object": "Exit"
									}
								}
							],
							"actions": [
								{
									"id": "go-to-layout",
									"objectClass": "System",
									"sid": 277513631807337,
									"parameters": {
										"layout": "Exit"
									}
								}
							],
							"sid": 993484501310869
						}
					],
					"sid": 192875353931914
				},
				{
					"eventType": "group",
					"disabled": false,
					"title": "Combat",
					"description": "",
					"isActiveOnStart": true,
					"children": [
						{
							"eventType": "block",
							"conditions": [
								{
									"id": "on-click",
									"objectClass": "Mouse",
									"sid": 855683952459833,
									"parameters": {
										"mouse-button": "left",
										"click-type": "clicked"
									}
								},
								{
									"id": "mouse-button-is-down",
									"objectClass": "Mouse",
									"sid": 816499232793303,
									"parameters": {
										"mouse-button": "right"
									},
									"isInverted": true
								},
								{
									"id": "is-boolean-instance-variable-set",
									"objectClass": "Player",
									"sid": 230796908209315,
									"parameters": {
										"instance-variable": "HasWeapon"
									}
								}
							],
							"actions": [
								{
									"id": "stop-animation",
									"objectClass": "Player",
									"sid": 924064440695770
								},
								{
									"id": "set-animation",
									"objectClass": "Player",
									"sid": 181262804454373,
									"parameters": {
										"animation": "\"Melee\"",
										"from": "beginning"
									}
								},
								{
									"id": "set-boolean-instvar",
									"objectClass": "Player",
									"sid": 337569487013890,
									"parameters": {
										"instance-variable": "isAttacking",
										"value": "true"
									}
								},
								{
									"id": "wait",
									"objectClass": "System",
									"sid": 949958663494905,
									"parameters": {
										"seconds": "0.5"
									}
								},
								{
									"id": "set-boolean-instvar",
									"objectClass": "Player",
									"sid": 506602145401603,
									"parameters": {
										"instance-variable": "isAttacking",
										"value": "false"
									}
								},
								{
									"id": "set-animation",
									"objectClass": "Player",
									"sid": 871874876978943,
									"parameters": {
										"animation": "\"Idle\"",
										"from": "beginning"
									}
								}
							],
							"sid": 141044844983670
						},
						{
							"eventType": "block",
							"conditions": [
								{
									"id": "is-boolean-instance-variable-set",
									"objectClass": "Player",
									"sid": 842187432577068,
									"parameters": {
										"instance-variable": "isAttacking"
									}
								}
							],
							"actions": [
								{
									"id": "spawn-another-object",
									"objectClass": "Player",
									"sid": 492600511926603,
									"parameters": {
										"object": "HurtBox",
										"layer": "0",
										"image-point": "1",
										"create-hierarchy": false
									}
								}
							],
							"sid": 900853095097562,
							"children": [
								{
									"eventType": "block",
									"conditions": [
										{
											"id": "is-mirrored",
											"objectClass": "Player",
											"sid": 574058640311198
										}
									],
									"actions": [
										{
											"id": "set-mirrored",
											"objectClass": "HurtBox",
											"sid": 952817256374025,
											"parameters": {
												"state": "mirrored"
											}
										}
									],
									"sid": 224135982086754
								}
							]
						},
						{
							"eventType": "block",
							"conditions": [
								{
									"id": "is-boolean-instance-variable-set",
									"objectClass": "Player",
									"sid": 415319143237003,
									"parameters": {
										"instance-variable": "isAttacking"
									},
									"isInverted": true
								}
							],
							"actions": [
								{
									"id": "destroy",
									"objectClass": "HurtBox",
									"sid": 240749585305172
								}
							],
							"sid": 902414583638227
						},
						{
							"eventType": "block",
							"conditions": [
								{
									"id": "is-animation-playing",
									"objectClass": "Player",
									"sid": 937062195361056,
									"parameters": {
										"animation": "\"Melee\""
									}
								}
							],
							"actions": [],
							"sid": 357396311367310,
							"children": [
								{
									"eventType": "block",
									"conditions": [
										{
											"id": "compare-animation-frame",
											"objectClass": "Player",
											"sid": 393822404037332,
											"parameters": {
												"comparison": 0,
												"number": "3"
											}
										}
									],
									"actions": [],
									"sid": 194467890103061
								}
							]
						},
						{
							"eventType": "block",
							"conditions": [
								{
									"id": "else",
									"objectClass": "System",
									"sid": 253006166098167
								}
							],
							"actions": [],
							"sid": 498122575280809
						},
						{
							"eventType": "block",
							"conditions": [
								{
									"id": "on-collision-with-another-object",
									"objectClass": "HurtBox",
									"sid": 526127387573806,
									"parameters": {
										"object": "Enemies"
									}
								}
							],
							"actions": [
								{
									"id": "subtract-from-instvar",
									"objectClass": "Enemies",
									"sid": 759223224563595,
									"parameters": {
										"instance-variable": "Health",
										"value": "Player.MeleeAttackPower"
									}
								}
							],
							"sid": 271991598287417
						}
					],
					"sid": 196173743346148
				},
				{
					"eventType": "group",
					"disabled": false,
					"title": "Movement",
					"description": "",
					"isActiveOnStart": true,
					"children": [
						{
							"eventType": "block",
							"conditions": [
								{
									"id": "key-is-down",
									"objectClass": "Keyboard",
									"sid": 392132241436559,
									"parameters": {
										"key": 87
									}
								}
							],
							"actions": [
								{
									"id": "simulate-control",
									"objectClass": "Player",
									"sid": 973028183375817,
									"behaviorType": "8Direction",
									"parameters": {
										"control": "up"
									}
								}
							],
							"sid": 611735197677331
						},
						{
							"eventType": "block",
							"conditions": [
								{
									"id": "key-is-down",
									"objectClass": "Keyboard",
									"sid": 433268265569988,
									"parameters": {
										"key": 65
									}
								}
							],
							"actions": [
								{
									"id": "simulate-control",
									"objectClass": "Player",
									"sid": 124455473323040,
									"behaviorType": "8Direction",
									"parameters": {
										"control": "left"
									}
								},
								{
									"id": "set-mirrored",
									"objectClass": "Player",
									"sid": 619574563351264,
									"parameters": {
										"state": "mirrored"
									}
								}
							],
							"sid": 625493714682704
						},
						{
							"eventType": "block",
							"conditions": [
								{
									"id": "key-is-down",
									"objectClass": "Keyboard",
									"sid": 764391568264812,
									"parameters": {
										"key": 83
									}
								}
							],
							"actions": [
								{
									"id": "simulate-control",
									"objectClass": "Player",
									"sid": 245394520530381,
									"behaviorType": "8Direction",
									"parameters": {
										"control": "down"
									}
								}
							],
							"sid": 356747474617136
						},
						{
							"eventType": "block",
							"conditions": [
								{
									"id": "key-is-down",
									"objectClass": "Keyboard",
									"sid": 365607970584753,
									"parameters": {
										"key": 68
									}
								}
							],
							"actions": [
								{
									"id": "simulate-control",
									"objectClass": "Player",
									"sid": 505079714698732,
									"behaviorType": "8Direction",
									"parameters": {
										"control": "right"
									}
								},
								{
									"id": "set-mirrored",
									"objectClass": "Player",
									"sid": 575177348159350,
									"parameters": {
										"state": "not-mirrored"
									}
								}
							],
							"sid": 532648976418812
						},
						{
							"eventType": "block",
							"conditions": [
								{
									"id": "is-moving",
									"objectClass": "Player",
									"sid": 698557610007746,
									"behaviorType": "8Direction"
								},
								{
									"id": "is-boolean-instance-variable-set",
									"objectClass": "Player",
									"sid": 239719738894913,
									"parameters": {
										"instance-variable": "isAttacking"
									},
									"isInverted": true
								}
							],
							"actions": [],
							"sid": 647779456759502,
							"children": [
								{
									"eventType": "block",
									"conditions": [
										{
											"id": "is-boolean-instance-variable-set",
											"objectClass": "Player",
											"sid": 734973243531368,
											"parameters": {
												"instance-variable": "HasWeapon"
											}
										}
									],
									"actions": [
										{
											"id": "set-animation",
											"objectClass": "Player",
											"sid": 508837892588834,
											"parameters": {
												"animation": "\"Run\"",
												"from": "beginning"
											}
										}
									],
									"sid": 100450411816738
								},
								{
									"eventType": "block",
									"conditions": [
										{
											"id": "is-boolean-instance-variable-set",
											"objectClass": "Player",
											"sid": 119132745675033,
											"parameters": {
												"instance-variable": "HasWeapon"
											},
											"isInverted": true
										}
									],
									"actions": [
										{
											"id": "set-animation",
											"objectClass": "Player",
											"sid": 697268053517459,
											"parameters": {
												"animation": "\"RunNoWep\"",
												"from": "beginning"
											}
										}
									],
									"sid": 820069994668080
								}
							]
						},
						{
							"eventType": "block",
							"conditions": [
								{
									"id": "is-moving",
									"objectClass": "Player",
									"sid": 877593473327557,
									"behaviorType": "8Direction",
									"isInverted": true
								},
								{
									"id": "is-boolean-instance-variable-set",
									"objectClass": "Player",
									"sid": 735701495517833,
									"parameters": {
										"instance-variable": "isAttacking"
									},
									"isInverted": true
								}
							],
							"actions": [],
							"sid": 419602104576872,
							"children": [
								{
									"eventType": "block",
									"conditions": [
										{
											"id": "is-boolean-instance-variable-set",
											"objectClass": "Player",
											"sid": 481059079982434,
											"parameters": {
												"instance-variable": "HasWeapon"
											}
										}
									],
									"actions": [
										{
											"id": "set-animation",
											"objectClass": "Player",
											"sid": 417956393575132,
											"parameters": {
												"animation": "\"Idle\"",
												"from": "beginning"
											}
										}
									],
									"sid": 264904566087730
								},
								{
									"eventType": "block",
									"conditions": [
										{
											"id": "is-boolean-instance-variable-set",
											"objectClass": "Player",
											"sid": 648410482489056,
											"parameters": {
												"instance-variable": "HasWeapon"
											},
											"isInverted": true
										}
									],
									"actions": [
										{
											"id": "set-animation",
											"objectClass": "Player",
											"sid": 785895289127206,
											"parameters": {
												"animation": "\"IdleNoWep\"",
												"from": "beginning"
											}
										}
									],
									"sid": 362907080839895
								}
							]
						}
					],
					"sid": 878660020022571
				}
			],
			"sid": 908067233360411
		},
		{
			"eventType": "group",
			"disabled": false,
			"title": "EnemyFunctions",
			"description": "",
			"isActiveOnStart": true,
			"children": [
				{
					"eventType": "group",
					"disabled": false,
					"title": "Melee",
					"description": "",
					"isActiveOnStart": true,
					"children": [
						{
							"eventType": "block",
							"conditions": [
								{
									"id": "has-los-to-object",
									"objectClass": "MeleeEnemy",
									"sid": 528923403554994,
									"behaviorType": "LineOfSight",
									"parameters": {
										"object": "Player",
										"image-point": "0"
									},
									"isInverted": true
								}
							],
							"actions": [
								{
									"id": "stop",
									"objectClass": "MeleeEnemy",
									"sid": 586859436128927,
									"behaviorType": "MoveTo"
								}
							],
							"sid": 402131777083533
						},
						{
							"eventType": "block",
							"conditions": [
								{
									"id": "has-los-to-object",
									"objectClass": "MeleeEnemy",
									"sid": 779173926088564,
									"behaviorType": "LineOfSight",
									"parameters": {
										"object": "Player",
										"image-point": "0"
									}
								},
								{
									"id": "is-overlapping-another-object",
									"objectClass": "MeleeEnemy",
									"sid": 114968632231947,
									"parameters": {
										"object": "Player"
									},
									"isInverted": true
								}
							],
							"actions": [
								{
									"id": "move-to-object",
									"objectClass": "MeleeEnemy",
									"sid": 544026260534270,
									"behaviorType": "MoveTo",
									"parameters": {
										"object": "Player",
										"image-point": "0",
										"mode": "direct"
									}
								}
							],
							"sid": 389852045157623
						},
						{
							"eventType": "block",
							"conditions": [
								{
									"id": "is-overlapping-another-object",
									"objectClass": "MeleeEnemy",
									"sid": 562424117664141,
									"parameters": {
										"object": "Player"
									}
								}
							],
							"actions": [
								{
									"id": "set-animation",
									"objectClass": "MeleeEnemy",
									"sid": 331567805753787,
									"parameters": {
										"animation": "\"Attack\"",
										"from": "beginning"
									}
								},
								{
									"id": "stop",
									"objectClass": "MeleeEnemy",
									"sid": 214306275772286,
									"behaviorType": "MoveTo"
								}
							],
							"sid": 199252484408551
						},
						{
							"eventType": "block",
							"conditions": [
								{
									"id": "is-moving",
									"objectClass": "MeleeEnemy",
									"sid": 361367507526509,
									"behaviorType": "MoveTo"
								},
								{
									"id": "is-overlapping-another-object",
									"objectClass": "MeleeEnemy",
									"sid": 287690171379512,
									"parameters": {
										"object": "Player"
									},
									"isInverted": true
								}
							],
							"actions": [
								{
									"id": "set-animation",
									"objectClass": "MeleeEnemy",
									"sid": 161259310962602,
									"parameters": {
										"animation": "\"Walk\"",
										"from": "beginning"
									}
								}
							],
							"sid": 947718156981577
						},
						{
							"eventType": "block",
							"conditions": [
								{
									"id": "is-moving",
									"objectClass": "MeleeEnemy",
									"sid": 533224124211080,
									"behaviorType": "MoveTo",
									"isInverted": true
								},
								{
									"id": "is-overlapping-another-object",
									"objectClass": "MeleeEnemy",
									"sid": 157572636584614,
									"parameters": {
										"object": "Player"
									},
									"isInverted": true
								}
							],
							"actions": [
								{
									"id": "set-animation",
									"objectClass": "MeleeEnemy",
									"sid": 205930013070566,
									"parameters": {
										"animation": "\"Idle\"",
										"from": "beginning"
									}
								}
							],
							"sid": 650060510421068
						},
						{
							"eventType": "block",
							"conditions": [
								{
									"id": "is-animation-playing",
									"objectClass": "MeleeEnemy",
									"sid": 677501487869777,
									"parameters": {
										"animation": "\"Attack\""
									}
								}
							],
							"actions": [],
							"sid": 731825691552742,
							"children": [
								{
									"eventType": "block",
									"conditions": [
										{
											"id": "every-x-seconds",
											"objectClass": "System",
											"sid": 603172948068098,
											"parameters": {
												"interval-seconds": "2"
											}
										}
									],
									"actions": [
										{
											"id": "subtract-from-instvar",
											"objectClass": "Player",
											"sid": 934469631727534,
											"parameters": {
												"instance-variable": "Health",
												"value": "MeleeEnemy.AttackPower"
											}
										}
									],
									"sid": 157380121596148
								}
							]
						}
					],
					"sid": 598545483514460
				},
				{
					"eventType": "group",
					"disabled": false,
					"title": "Ranged",
					"description": "",
					"isActiveOnStart": true,
					"children": [
						{
							"eventType": "block",
							"conditions": [
								{
									"id": "has-los-to-object",
									"objectClass": "RangedEnemy",
									"sid": 336946129881526,
									"behaviorType": "LineOfSight",
									"parameters": {
										"object": "Player",
										"image-point": "0"
									}
								}
							],
							"actions": [
								{
									"id": "acquire-target",
									"objectClass": "RangedEnemy",
									"sid": 599893981576899,
									"behaviorType": "Turret",
									"parameters": {
										"target": "Player"
									}
								}
							],
							"sid": 167243616117189
						},
						{
							"eventType": "block",
							"conditions": [
								{
									"id": "has-los-to-object",
									"objectClass": "RangedEnemy",
									"sid": 531931654273194,
									"behaviorType": "LineOfSight",
									"parameters": {
										"object": "Player",
										"image-point": "0"
									},
									"isInverted": true
								}
							],
							"actions": [
								{
									"id": "unacquire-target",
									"objectClass": "RangedEnemy",
									"sid": 645941691617525,
									"behaviorType": "Turret"
								},
								{
									"id": "set-animation",
									"objectClass": "RangedEnemy",
									"sid": 943779641461507,
									"parameters": {
										"animation": "\"Idle\"",
										"from": "beginning"
									}
								}
							],
							"sid": 805496366159830
						},
						{
							"eventType": "block",
							"conditions": [
								{
									"id": "on-shoot",
									"objectClass": "RangedEnemy",
									"sid": 545073456553194,
									"behaviorType": "Turret"
								}
							],
							"actions": [
								{
									"id": "set-animation",
									"objectClass": "RangedEnemy",
									"sid": 112022779447862,
									"parameters": {
										"animation": "\"Fire\"",
										"from": "beginning"
									}
								},
								{
									"id": "spawn-another-object",
									"objectClass": "RangedEnemy",
									"sid": 324701539906347,
									"parameters": {
										"object": "ProjEnemyArrows",
										"layer": "0",
										"image-point": "1",
										"create-hierarchy": false
									}
								},
								{
									"id": "set-speed",
									"objectClass": "ProjEnemyArrows",
									"sid": 854773087603900,
									"behaviorType": "Bullet",
									"parameters": {
										"speed": "400\n"
									}
								}
							],
							"sid": 543153719596535
						},
						{
							"eventType": "block",
							"conditions": [
								{
									"id": "on-collision-with-another-object",
									"objectClass": "ProjEnemyArrows",
									"sid": 851040654154095,
									"parameters": {
										"object": "Player"
									}
								}
							],
							"actions": [
								{
									"id": "subtract-from-instvar",
									"objectClass": "Player",
									"sid": 304810276705884,
									"parameters": {
										"instance-variable": "Health",
										"value": "1"
									}
								}
							],
							"sid": 556451151512212
						}
					],
					"sid": 325755790949201
				},
				{
					"eventType": "block",
					"conditions": [
						{
							"id": "on-collision-with-another-object",
							"objectClass": "ProjEnemyArrows",
							"sid": 302499155883922,
							"parameters": {
								"object": "TiMWalls"
							}
						}
					],
					"actions": [
						{
							"id": "destroy",
							"objectClass": "ProjEnemyArrows",
							"sid": 139880984243209
						}
					],
					"sid": 970100203333347
				},
				{
					"eventType": "block",
					"conditions": [
						{
							"id": "compare-instance-variable",
							"objectClass": "Enemies",
							"sid": 106124329299171,
							"parameters": {
								"instance-variable": "Health",
								"comparison": 3,
								"value": "0"
							}
						}
					],
					"actions": [
						{
							"id": "destroy",
							"objectClass": "Enemies",
							"sid": 138237156877586
						},
						{
							"id": "add-to-instvar",
							"objectClass": "Player",
							"sid": 591905873548474,
							"parameters": {
								"instance-variable": "Experience",
								"value": "5"
							}
						}
					],
					"sid": 856962707142418
				},
				{
					"eventType": "block",
					"conditions": [
						{
							"id": "every-tick",
							"objectClass": "System",
							"sid": 849024393316672
						}
					],
					"actions": [],
					"sid": 181898316237415
				},
				{
					"eventType": "block",
					"conditions": [
						{
							"id": "on-start-of-layout",
							"objectClass": "System",
							"sid": 693943139616212
						}
					],
					"actions": [
						{
							"id": "set-instvar-value",
							"objectClass": "Enemies",
							"sid": 440437824460494,
							"parameters": {
								"instance-variable": "StartingPosX",
								"value": "Enemies.X"
							}
						},
						{
							"id": "set-instvar-value",
							"objectClass": "Enemies",
							"sid": 921191504337874,
							"parameters": {
								"instance-variable": "StartingPosY",
								"value": "Enemies.Y"
							}
						}
					],
					"sid": 411950803960130
				}
			],
			"sid": 634572696499043
		},
		{
			"eventType": "group",
			"disabled": false,
			"title": "Chests",
			"description": "",
			"isActiveOnStart": true,
			"children": [
				{
					"eventType": "block",
					"conditions": [
						{
							"id": "on-start-of-layout",
							"objectClass": "System",
							"sid": 182350827949867
						}
					],
					"actions": [],
					"sid": 352196123032714,
					"children": [
						{
							"eventType": "block",
							"conditions": [
								{
									"id": "compare-instance-variable",
									"objectClass": "Chest",
									"sid": 614531778653804,
									"parameters": {
										"instance-variable": "KeyType",
										"comparison": 0,
										"value": "1"
									}
								}
							],
							"actions": [
								{
									"id": "set-animation",
									"objectClass": "Chest",
									"sid": 691057879721170,
									"parameters": {
										"animation": "\"Skeleton\"",
										"from": "beginning"
									}
								}
							],
							"sid": 604694237960273
						},
						{
							"eventType": "block",
							"conditions": [
								{
									"id": "compare-instance-variable",
									"objectClass": "Chest",
									"sid": 912103271769933,
									"parameters": {
										"instance-variable": "KeyType",
										"comparison": 0,
										"value": "0"
									}
								}
							],
							"actions": [
								{
									"id": "set-animation",
									"objectClass": "Chest",
									"sid": 819712832063745,
									"parameters": {
										"animation": "\"Normal\"",
										"from": "beginning"
									}
								}
							],
							"sid": 895203323947621
						}
					]
				}
			],
			"sid": 323344076744954
		},
		{
			"eventType": "block",
			"conditions": [
				{
					"id": "every-tick",
					"objectClass": "System",
					"sid": 837758532685685
				}
			],
			"actions": [
				{
					"id": "set-text",
					"objectClass": "TxtHealth",
					"sid": 694693393282865,
					"parameters": {
						"text": "\"Health: \" & Player.Health"
					}
				},
				{
					"id": "set-text",
					"objectClass": "TxtLevel",
					"sid": 191006376825840,
					"parameters": {
						"text": "\"Level: \"& Player.Level"
					}
				},
				{
					"id": "add-obstacle",
					"objectClass": "RangedEnemy",
					"sid": 416101324156497,
					"behaviorType": "LineOfSight",
					"parameters": {
						"obstacle": "TiMWalls"
					}
				},
				{
					"id": "set-visible",
					"objectClass": "HurtBox",
					"sid": 716137718679026,
					"parameters": {
						"visibility": "invisible"
					}
				}
			],
			"sid": 503538702123367
		}
	],
	"sid": 843601103535796
}